logorestclient/__init__.py
logorestclient/exceptions.py
logorestclient/serializer.py
logorestclient/helper/__init__.py
logorestclient/helper/sqlite.py
logorestclient/helper/token.py
logorestclient/service/__init__.py
logorestclient/service/http_service.py
logorestclient/service/logo_service.py
logorestclient/service/token_service.py
LogoRestClient-0.0.6.dist-info/LICENSE
LogoRestClient-0.0.6.dist-info/METADATA
LogoRestClient-0.0.6.dist-info/WHEEL
LogoRestClient-0.0.6.dist-info/top_level.txt
LogoRestClient-0.0.6.dist-info/RECORD
