Metadata-Version: 2.1
Name: LogoRestClient
Version: 0.0.6
Summary: Logo Rest Client Python package
Home-page: https://github.com/blueromans/LogoRestClient.git
Author: Yaşar Özyurt
Author-email: blueromans@gmail.com
Project-URL: Bug Tracker, https://github.com/blueromans/LogoRestClient/issues
Classifier: Programming Language :: Python :: 3
Classifier: License :: OSI Approved :: MIT License
Classifier: Operating System :: OS Independent
Requires-Python: >=3.6
License-File: LICENSE
Requires-Dist: requests
